{
  "abort_bad_kmeans_init": true,
  "batch_size": 8,
  "c1_ch": 16,
  "cpu": false,
  "data_dir": "/workspace/yongjia/datasets/DIV2K",
  "epochs": 800,
  "init_ckpt": "MY/jscc-no-awgn/cvq_v2_c36_stage0_best.pth",
  "init_codebook_from_jscc": false,
  "init_codebook_method": "random_normal",
  "init_jscc_decoder": "",
  "init_jscc_encoder": "",
  "k": 16384,
  "kmeans_assign_chunk": 4096,
  "kmeans_device": "",
  "kmeans_iters": 30,
  "lambda_all_z": 0.01,
  "lambda_c1": 0.0,
  "lambda_drop": 0.0,
  "lambda_full": 1.0,
  "lambda_usage_entropy": 0.0,
  "lambda_usage_topk": 0.0,
  "lambda_vq": 0.05,
  "latent_cache_maps": 262144,
  "latent_cache_path": "",
  "latent_ch": 36,
  "latent_h": 16,
  "latent_w": 16,
  "latest_every": 10,
  "log_file": "/workspace/yongjia/paper_code/CDDM/MY/VQ-Stage1/stage1_cvq_v2_c36_snr12_k16384-simvq-all-z.log",
  "max_init_quant_mse": 0.15,
  "min_init_psnr_q_full": 20.0,
  "nested_drop_ratio": 1.0,
  "num_workers": 16,
  "random_codebook_std": 0.02,
  "reuse_latent_cache": true,
  "save_dir": "/workspace/yongjia/paper_code/CDDM/MY/VQ-Stage1",
  "scaled_vq_eps": 1e-06,
  "scaled_vq_random_codebook_std": 1.0,
  "scaled_vq_stat_batches": 0,
  "seed": 20260610,
  "simvq_codebook_std": 0.0,
  "simvq_legacy": true,
  "simvq_proj_bias": true,
  "simvq_train_codebook": false,
  "snr_db": 12.0,
  "stage": 1,
  "stage1_codebook_lr_phase1": 0.0005,
  "stage1_codebook_lr_phase2": 0.0001,
  "stage1_codebook_lr_phase3": 5e-05,
  "stage1_codebook_update": "ema",
  "stage1_decoder_lr_phase1": 0.0,
  "stage1_decoder_lr_phase2": 1e-05,
  "stage1_decoder_lr_phase3": 1e-05,
  "stage1_encoder_lr_phase1": 0.0,
  "stage1_encoder_lr_phase2": 0.0,
  "stage1_encoder_lr_phase3": 1e-05,
  "stage1_phase1_end_epoch": 0,
  "stage1_phase2_end_epoch": 0,
  "stage1_vq_mode": "simvq",
  "test_batch": 1,
  "usage_reg_chunk_size": 128,
  "usage_reg_detach_codebook": true,
  "usage_reg_eps": 1e-08,
  "usage_reg_eval": false,
  "usage_reg_tau": 1.0,
  "usage_reg_top10_target": 0.25,
  "usage_reg_top1_target": 0.05,
  "val_every": 5,
  "val_num_workers": 8,
  "version": "simvq-all-z",
  "vq_beta": 0.25,
  "vq_chunk_size": 128,
  "vq_ema_decay": 0.99,
  "vq_ema_eps": 1e-05,
  "vq_ema_initial_count": 1.0
}