[
  {
    "epoch": 1,
    "train": {
      "loss": 0.0020453227864345534,
      "loss_recon": 0.001056828125147149,
      "loss_vq": 0.0,
      "loss_monotonic": 0.0,
      "loss_q_relevance": 0.0,
      "loss_zero_anchor": 0.0,
      "loss_direct_gain": 0.0,
      "loss_teacher_final": 0.0009884946687816409,
      "loss_teacher_u2": 0.00959652681252919,
      "loss_prior_ce": 0.0,
      "loss_predictability": 0.0,
      "prior_assignment_entropy": 0.0,
      "prior_index_accuracy": 0.0,
      "loss_soft_usage": 0.0,
      "soft_usage_entropy_ratio": 0.0,
      "psnr_x1": 30.32561460494995,
      "psnr_source_teacher": 43.15489128112793,
      "delta_x1_source_teacher": 12.829276676177978,
      "train_channels_kept_mean": 182.60375,
      "psnr_k16384": 33.79502630233765,
      "delta_x1_k16384": 3.469411622285843,
      "vq_mse_k16384": 0.0,
      "continuous_q_warmup": 1.0,
      "used_k16384": 0.0,
      "ppl_k16384": 0.0,
      "ppl_ratio_k16384": 0.0,
      "top1_k16384": 0.0,
      "tokens_per_image_k16384": 240.0,
      "bits_per_image_k16384": 3360.0,
      "bpp_k16384": 0.05126953125
    }
  },
  {
    "epoch": 2,
    "train": {
      "loss": 0.0019063162588281557,
      "loss_recon": 0.0009855340288049774,
      "loss_vq": 0.0,
      "loss_monotonic": 0.0,
      "loss_q_relevance": 0.0,
      "loss_zero_anchor": 0.0,
      "loss_direct_gain": 0.0,
      "loss_teacher_final": 0.0009207822292955825,
      "loss_teacher_u2": 0.011235347834881395,
      "loss_prior_ce": 0.0,
      "loss_predictability": 0.0,
      "prior_assignment_entropy": 0.0,
      "prior_index_accuracy": 0.0,
      "loss_soft_usage": 0.0,
      "soft_usage_entropy_ratio": 0.0,
      "psnr_x1": 30.481331577301024,
      "psnr_source_teacher": 43.33154582977295,
      "delta_x1_source_teacher": 12.850213670730591,
      "train_channels_kept_mean": 183.60375,
      "psnr_k16384": 35.637436141967775,
      "delta_x1_k16384": 5.156104714870453,
      "vq_mse_k16384": 0.0,
      "continuous_q_warmup": 1.0,
      "used_k16384": 0.0,
      "ppl_k16384": 0.0,
      "ppl_ratio_k16384": 0.0,
      "top1_k16384": 0.0,
      "tokens_per_image_k16384": 240.0,
      "bits_per_image_k16384": 3360.0,
      "bpp_k16384": 0.05126953125
    }
  },
  {
    "epoch": 3,
    "train": {
      "loss": 0.0020068289191112853,
      "loss_recon": 0.0010364722369558877,
      "loss_vq": 0.0,
      "loss_monotonic": 0.0,
      "loss_q_relevance": 0.0,
      "loss_zero_anchor": 0.0,
      "loss_direct_gain": 0.0,
      "loss_teacher_final": 0.0009703566767711891,
      "loss_teacher_u2": 0.011796357459388673,
      "loss_prior_ce": 0.0,
      "loss_predictability": 0.0,
      "prior_assignment_entropy": 0.0,
      "prior_index_accuracy": 0.0,
      "loss_soft_usage": 0.0,
      "soft_usage_entropy_ratio": 0.0,
      "psnr_x1": 30.69172513961792,
      "psnr_source_teacher": 43.256967010498045,
      "delta_x1_source_teacher": 12.565241756439208,
      "train_channels_kept_mean": 174.70875,
      "psnr_k16384": 35.35408273696899,
      "delta_x1_k16384": 4.662357757091522,
      "vq_mse_k16384": 0.0,
      "continuous_q_warmup": 1.0,
      "used_k16384": 0.0,
      "ppl_k16384": 0.0,
      "ppl_ratio_k16384": 0.0,
      "top1_k16384": 0.0,
      "tokens_per_image_k16384": 240.0,
      "bits_per_image_k16384": 3360.0,
      "bpp_k16384": 0.05126953125
    }
  },
  {
    "epoch": 4,
    "train": {
      "loss": 0.0017946948541793972,
      "loss_recon": 0.0009296473556605633,
      "loss_vq": 0.0,
      "loss_monotonic": 0.0,
      "loss_q_relevance": 0.0,
      "loss_zero_anchor": 0.0,
      "loss_direct_gain": 0.0,
      "loss_teacher_final": 0.000865047492661688,
      "loss_teacher_u2": 0.011345627012196928,
      "loss_prior_ce": 0.0,
      "loss_predictability": 0.0,
      "prior_assignment_entropy": 0.0,
      "prior_index_accuracy": 0.0,
      "loss_soft_usage": 0.0,
      "soft_usage_entropy_ratio": 0.0,
      "psnr_x1": 30.788900966644288,
      "psnr_source_teacher": 43.349332084655764,
      "delta_x1_source_teacher": 12.56043116569519,
      "train_channels_kept_mean": 179.235,
      "psnr_k16384": 36.00703969955444,
      "delta_x1_k16384": 5.218138701915741,
      "vq_mse_k16384": 0.0,
      "continuous_q_warmup": 1.0,
      "used_k16384": 0.0,
      "ppl_k16384": 0.0,
      "ppl_ratio_k16384": 0.0,
      "top1_k16384": 0.0,
      "tokens_per_image_k16384": 240.0,
      "bits_per_image_k16384": 3360.0,
      "bpp_k16384": 0.05126953125
    }
  },
  {
    "epoch": 5,
    "train": {
      "loss": 0.0017867248870607,
      "loss_recon": 0.00092733113146096,
      "loss_vq": 0.0,
      "loss_monotonic": 0.0,
      "loss_q_relevance": 0.0,
      "loss_zero_anchor": 0.0,
      "loss_direct_gain": 0.0,
      "loss_teacher_final": 0.0008593937541081687,
      "loss_teacher_u2": 0.011109097169246525,
      "loss_prior_ce": 0.0,
      "loss_predictability": 0.0,
      "prior_assignment_entropy": 0.0,
      "prior_index_accuracy": 0.0,
      "loss_soft_usage": 0.0,
      "soft_usage_entropy_ratio": 0.0,
      "psnr_x1": 30.226882305145264,
      "psnr_source_teacher": 43.06699012756348,
      "delta_x1_source_teacher": 12.840107870101928,
      "train_channels_kept_mean": 182.38875,
      "psnr_k16384": 35.80059196472168,
      "delta_x1_k16384": 5.573709614276886,
      "vq_mse_k16384": 0.0,
      "continuous_q_warmup": 1.0,
      "used_k16384": 0.0,
      "ppl_k16384": 0.0,
      "ppl_ratio_k16384": 0.0,
      "top1_k16384": 0.0,
      "tokens_per_image_k16384": 240.0,
      "bits_per_image_k16384": 3360.0,
      "bpp_k16384": 0.05126953125
    },
    "val": {
      "loss": 0.0004999848199076951,
      "loss_recon": 0.0002775095752440393,
      "loss_vq": 0.0,
      "loss_monotonic": 0.0,
      "loss_q_relevance": 0.0,
      "loss_zero_anchor": 0.0,
      "loss_direct_gain": 0.0,
      "loss_teacher_final": 0.00022247524349950254,
      "loss_teacher_u2": 0.007924702875316143,
      "loss_prior_ce": 0.0,
      "loss_predictability": 0.0,
      "prior_assignment_entropy": 0.0,
      "prior_index_accuracy": 0.0,
      "loss_soft_usage": 0.0,
      "soft_usage_entropy_ratio": 0.0,
      "psnr_x1": 27.565001678466796,
      "psnr_source_teacher": 42.273160247802736,
      "delta_x1_source_teacher": 14.70815818786621,
      "psnr_k16384": 37.65132110595703,
      "delta_x1_k16384": 10.086319198608399,
      "vq_mse_k16384": 0.0,
      "drop_zero_k16384": 10.086319122314453,
      "drop_shuffle_k16384": 13.50829849243164,
      "continuous_q_warmup": 1.0,
      "used_k16384": 0.0,
      "ppl_k16384": 0.0,
      "ppl_ratio_k16384": 0.0,
      "top1_k16384": 0.0,
      "tokens_per_image_k16384": 240.0,
      "bits_per_image_k16384": 3360.0,
      "bpp_k16384": 0.05126953125,
      "codebook_l2_mean": 1.415730357170105,
      "codebook_l2_std": 0.06251123547554016,
      "codebook_l2_min": 1.1502889394760132,
      "codebook_l2_max": 1.6732618808746338,
      "codebook_l2_sample_size": 512.0,
      "codebook_effective_rank": 251.9102325439453,
      "codebook_stable_rank": 141.06472778320312,
      "codebook_numerical_rank": 256.0,
      "codebook_singular_top1_share": 0.005345845129340887,
      "codebook_rank_sample_size": 2048.0,
      "capacity_goal_met": 1.0,
      "noncollapse_goal_met": 0.0,
      "oracle_goal_met": 0.0,
      "continuous_goal_met": 1.0
    }
  },
  {
    "epoch": 6,
    "train": {
      "loss": 0.013160979333333671,
      "loss_recon": 0.002205705253290944,
      "loss_vq": 0.44171959832310675,
      "loss_monotonic": 0.0,
      "loss_q_relevance": 0.0,
      "loss_zero_anchor": 0.0,
      "loss_direct_gain": 0.0,
      "loss_teacher_final": 0.0021208823824417776,
      "loss_teacher_u2": 0.01250844148453325,
      "loss_prior_ce": 0.0,
      "loss_predictability": 0.0,
      "prior_assignment_entropy": 0.0,
      "prior_index_accuracy": 0.0,
      "loss_soft_usage": 0.0,
      "soft_usage_entropy_ratio": 0.0,
      "psnr_x1": 30.567008399963377,
      "psnr_source_teacher": 43.36463108062744,
      "delta_x1_source_teacher": 12.797622509002686,
      "train_channels_kept_mean": 179.22125,
      "psnr_k16384": 30.494630012512207,
      "delta_x1_k16384": -0.07237845182418823,
      "vq_mse_k16384": 0.3533756795525551,
      "continuous_q_warmup": 0.0,
      "used_k16384": 8435.0,
      "ppl_k16384": 3697.5135883386984,
      "ppl_ratio_k16384": 0.22567831960075063,
      "top1_k16384": 0.008484375,
      "tokens_per_image_k16384": 240.0,
      "bits_per_image_k16384": 3360.0,
      "bpp_k16384": 0.05126953125
    }
  },
  {
    "epoch": 7,
    "train": {
      "loss": 0.015284433767665178,
      "loss_recon": 0.0022539449812029487,
      "loss_vq": 0.5431339567899705,
      "loss_monotonic": 0.0,
      "loss_q_relevance": 0.0,
      "loss_zero_anchor": 0.0,
      "loss_direct_gain": 0.0,
      "loss_teacher_final": 0.0021678099839482455,
      "loss_teacher_u2": 0.014287392632104457,
      "loss_prior_ce": 0.0,
      "loss_predictability": 0.0,
      "prior_assignment_entropy": 0.0,
      "prior_index_accuracy": 0.0,
      "loss_soft_usage": 0.0,
      "soft_usage_entropy_ratio": 0.0,
      "psnr_x1": 30.650960044860838,
      "psnr_source_teacher": 43.2058239364624,
      "delta_x1_source_teacher": 12.554863834381104,
      "train_channels_kept_mean": 184.31,
      "psnr_k16384": 30.633516273498536,
      "delta_x1_k16384": -0.017443597316741943,
      "vq_mse_k16384": 0.4345071681588888,
      "continuous_q_warmup": 0.0,
      "used_k16384": 9125.0,
      "ppl_k16384": 3828.09599381093,
      "ppl_ratio_k16384": 0.23364843712224914,
      "top1_k16384": 0.011125,
      "tokens_per_image_k16384": 240.0,
      "bits_per_image_k16384": 3360.0,
      "bpp_k16384": 0.05126953125
    }
  },
  {
    "epoch": 8,
    "train": {
      "loss": 0.015790867134928704,
      "loss_recon": 0.002242619327735156,
      "loss_vq": 0.5693490567058325,
      "loss_monotonic": 0.0,
      "loss_q_relevance": 0.0,
      "loss_zero_anchor": 0.0,
      "loss_direct_gain": 0.0,
      "loss_teacher_final": 0.0021612670039758085,
      "loss_teacher_u2": 0.014285391326993704,
      "loss_prior_ce": 0.0,
      "loss_predictability": 0.0,
      "prior_assignment_entropy": 0.0,
      "prior_index_accuracy": 0.0,
      "loss_soft_usage": 0.0,
      "soft_usage_entropy_ratio": 0.0,
      "psnr_x1": 30.511182079315187,
      "psnr_source_teacher": 43.29182300567627,
      "delta_x1_source_teacher": 12.780640888214112,
      "train_channels_kept_mean": 188.19375,
      "psnr_k16384": 30.543712272644044,
      "delta_x1_k16384": 0.0325301194190979,
      "vq_mse_k16384": 0.45547924473881723,
      "continuous_q_warmup": 0.0,
      "used_k16384": 9470.0,
      "ppl_k16384": 3920.086925171031,
      "ppl_ratio_k16384": 0.23926311799139593,
      "top1_k16384": 0.012567708333333334,
      "tokens_per_image_k16384": 240.0,
      "bits_per_image_k16384": 3360.0,
      "bpp_k16384": 0.05126953125
    }
  },
  {
    "epoch": 9,
    "train": {
      "loss": 0.014516848963685334,
      "loss_recon": 0.0022122815842158163,
      "loss_vq": 0.5087703516334295,
      "loss_monotonic": 0.0,
      "loss_q_relevance": 0.0,
      "loss_zero_anchor": 0.0,
      "loss_direct_gain": 0.0,
      "loss_teacher_final": 0.002129160590702668,
      "loss_teacher_u2": 0.013094738558866083,
      "loss_prior_ce": 0.0,
      "loss_predictability": 0.0,
      "prior_assignment_entropy": 0.0,
      "prior_index_accuracy": 0.0,
      "loss_soft_usage": 0.0,
      "soft_usage_entropy_ratio": 0.0,
      "psnr_x1": 30.42061840057373,
      "psnr_source_teacher": 43.28948062896728,
      "delta_x1_source_teacher": 12.868861846923828,
      "train_channels_kept_mean": 168.6525,
      "psnr_k16384": 30.436484451293946,
      "delta_x1_k16384": 0.01586602449417114,
      "vq_mse_k16384": 0.4070162830501795,
      "continuous_q_warmup": 0.0,
      "used_k16384": 9525.0,
      "ppl_k16384": 3807.4026419410943,
      "ppl_ratio_k16384": 0.2323854151575375,
      "top1_k16384": 0.015369791666666667,
      "tokens_per_image_k16384": 240.0,
      "bits_per_image_k16384": 3360.0,
      "bpp_k16384": 0.05126953125
    }
  },
  {
    "epoch": 10,
    "train": {
      "loss": 0.014938698410987853,
      "loss_recon": 0.0023411787740769798,
      "loss_vq": 0.5175271824747324,
      "loss_monotonic": 0.0,
      "loss_q_relevance": 0.0,
      "loss_zero_anchor": 0.0,
      "loss_direct_gain": 0.0,
      "loss_teacher_final": 0.002246976081514731,
      "loss_teacher_u2": 0.013403247613459825,
      "loss_prior_ce": 0.0,
      "loss_predictability": 0.0,
      "prior_assignment_entropy": 0.0,
      "prior_index_accuracy": 0.0,
      "loss_soft_usage": 0.0,
      "soft_usage_entropy_ratio": 0.0,
      "psnr_x1": 30.447985153198243,
      "psnr_source_teacher": 43.17595699310303,
      "delta_x1_source_teacher": 12.7279718875885,
      "train_channels_kept_mean": 168.7075,
      "psnr_k16384": 30.501682586669922,
      "delta_x1_k16384": 0.0536971116065979,
      "vq_mse_k16384": 0.41402174726128577,
      "continuous_q_warmup": 0.0,
      "used_k16384": 9505.0,
      "ppl_k16384": 3561.2830695541597,
      "ppl_ratio_k16384": 0.21736346860071776,
      "top1_k16384": 0.019677083333333335,
      "tokens_per_image_k16384": 240.0,
      "bits_per_image_k16384": 3360.0,
      "bpp_k16384": 0.05126953125
    },
    "val": {
      "loss": 0.023830889016389845,
      "loss_recon": 0.0026737055089324714,
      "loss_vq": 0.9289553737640381,
      "loss_monotonic": 0.0,
      "loss_q_relevance": 0.0,
      "loss_zero_anchor": 0.0,
      "loss_direct_gain": 0.0,
      "loss_teacher_final": 0.0025780768599361183,
      "loss_teacher_u2": 0.011976597793400288,
      "loss_prior_ce": 0.0,
      "loss_predictability": 0.0,
      "prior_assignment_entropy": 0.0,
      "prior_index_accuracy": 0.0,
      "loss_soft_usage": 0.0,
      "soft_usage_entropy_ratio": 0.0,
      "psnr_x1": 27.565001678466796,
      "psnr_source_teacher": 42.273160247802736,
      "delta_x1_source_teacher": 14.70815818786621,
      "psnr_k16384": 27.72329750061035,
      "delta_x1_k16384": 0.15829538345336913,
      "vq_mse_k16384": 0.7431642985343934,
      "drop_zero_k16384": 0.1582953643798828,
      "drop_shuffle_k16384": 0.9087293243408203,
      "continuous_q_warmup": 0.0,
      "used_k16384": 6624.0,
      "ppl_k16384": 4894.067500603533,
      "ppl_ratio_k16384": 0.2987101745973836,
      "top1_k16384": 0.00125,
      "tokens_per_image_k16384": 240.0,
      "bits_per_image_k16384": 3360.0,
      "bpp_k16384": 0.05126953125,
      "codebook_l2_mean": 12.574572563171387,
      "codebook_l2_std": 6.03731632232666,
      "codebook_l2_min": 0.009744325652718544,
      "codebook_l2_max": 66.94806671142578,
      "codebook_l2_sample_size": 512.0,
      "codebook_effective_rank": 240.8064727783203,
      "codebook_stable_rank": 8.470900535583496,
      "codebook_numerical_rank": 256.0,
      "codebook_singular_top1_share": 0.023276453837752342,
      "codebook_rank_sample_size": 2048.0,
      "capacity_goal_met": 1.0,
      "noncollapse_goal_met": 1.0,
      "oracle_goal_met": 1.0
    }
  },
  {
    "epoch": 11,
    "train": {
      "loss": 0.01675079873763025,
      "loss_recon": 0.0023358871479285882,
      "loss_vq": 0.6084246304631233,
      "loss_monotonic": 0.0,
      "loss_q_relevance": 0.0,
      "loss_zero_anchor": 0.0,
      "loss_direct_gain": 0.0,
      "loss_teacher_final": 0.002246419253060594,
      "loss_teacher_u2": 0.013706602931488305,
      "loss_prior_ce": 0.0,
      "loss_predictability": 0.0,
      "prior_assignment_entropy": 0.0,
      "prior_index_accuracy": 0.0,
      "loss_soft_usage": 0.0,
      "soft_usage_entropy_ratio": 0.0,
      "psnr_x1": 30.397245674133302,
      "psnr_source_teacher": 43.27227912902832,
      "delta_x1_source_teacher": 12.875033254623412,
      "train_channels_kept_mean": 180.53625,
      "psnr_k16384": 30.427368698120116,
      "delta_x1_k16384": 0.03012301802635193,
      "vq_mse_k16384": 0.4867397041618824,
      "continuous_q_warmup": 0.0,
      "used_k16384": 9905.0,
      "ppl_k16384": 3998.3423410392106,
      "ppl_ratio_k16384": 0.244039449526319,
      "top1_k16384": 0.016994791666666665,
      "tokens_per_image_k16384": 240.0,
      "bits_per_image_k16384": 3360.0,
      "bpp_k16384": 0.05126953125
    }
  },
  {
    "epoch": 12,
    "train": {
      "loss": 0.01632200653431937,
      "loss_recon": 0.0023010896617779507,
      "loss_vq": 0.5903593531250954,
      "loss_monotonic": 0.0,
      "loss_q_relevance": 0.0,
      "loss_zero_anchor": 0.0,
      "loss_direct_gain": 0.0,
      "loss_teacher_final": 0.0022137301112525164,
      "loss_teacher_u2": 0.013820093008689582,
      "loss_prior_ce": 0.0,
      "loss_predictability": 0.0,
      "prior_assignment_entropy": 0.0,
      "prior_index_accuracy": 0.0,
      "loss_soft_usage": 0.0,
      "soft_usage_entropy_ratio": 0.0,
      "psnr_x1": 30.161832065582274,
      "psnr_source_teacher": 43.170058746337894,
      "delta_x1_source_teacher": 13.008226737976074,
      "train_channels_kept_mean": 183.81875,
      "psnr_k16384": 30.21042875289917,
      "delta_x1_k16384": 0.04859674215316773,
      "vq_mse_k16384": 0.47228748179972174,
      "continuous_q_warmup": 0.0,
      "used_k16384": 9832.0,
      "ppl_k16384": 4070.1451472033573,
      "ppl_ratio_k16384": 0.24842194501973616,
      "top1_k16384": 0.014723958333333334,
      "tokens_per_image_k16384": 240.0,
      "bits_per_image_k16384": 3360.0,
      "bpp_k16384": 0.05126953125
    }
  },
  {
    "epoch": 13,
    "train": {
      "loss": 0.01671478662872687,
      "loss_recon": 0.0023194398570922205,
      "loss_vq": 0.6082076998054982,
      "loss_monotonic": 0.0,
      "loss_q_relevance": 0.0,
      "loss_zero_anchor": 0.0,
      "loss_direct_gain": 0.0,
      "loss_teacher_final": 0.002231193172337953,
      "loss_teacher_u2": 0.013021377152763308,
      "loss_prior_ce": 0.0,
      "loss_predictability": 0.0,
      "prior_assignment_entropy": 0.0,
      "prior_index_accuracy": 0.0,
      "loss_soft_usage": 0.0,
      "soft_usage_entropy_ratio": 0.0,
      "psnr_x1": 30.422018909454344,
      "psnr_source_teacher": 43.261477584838865,
      "delta_x1_source_teacher": 12.839458599090577,
      "train_channels_kept_mean": 182.4575,
      "psnr_k16384": 30.477356128692627,
      "delta_x1_k16384": 0.05533695459365845,
      "vq_mse_k16384": 0.48656616151332854,
      "continuous_q_warmup": 0.0,
      "used_k16384": 10128.0,
      "ppl_k16384": 3836.605202415955,
      "ppl_ratio_k16384": 0.23416779799902068,
      "top1_k16384": 0.020822916666666667,
      "tokens_per_image_k16384": 240.0,
      "bits_per_image_k16384": 3360.0,
      "bpp_k16384": 0.05126953125
    }
  },
  {
    "epoch": 14,
    "train": {
      "loss": 0.01627611088566482,
      "loss_recon": 0.002285960124572739,
      "loss_vq": 0.5896385569125414,
      "loss_monotonic": 0.0,
      "loss_q_relevance": 0.0,
      "loss_zero_anchor": 0.0,
      "loss_direct_gain": 0.0,
      "loss_teacher_final": 0.0021973799460101875,
      "loss_teacher_u2": 0.014514570496976376,
      "loss_prior_ce": 0.0,
      "loss_predictability": 0.0,
      "prior_assignment_entropy": 0.0,
      "prior_index_accuracy": 0.0,
      "loss_soft_usage": 0.0,
      "soft_usage_entropy_ratio": 0.0,
      "psnr_x1": 30.42907480239868,
      "psnr_source_teacher": 43.26427207946777,
      "delta_x1_source_teacher": 12.835197381973266,
      "train_channels_kept_mean": 183.405,
      "psnr_k16384": 30.513625507354735,
      "delta_x1_k16384": 0.08455094575881958,
      "vq_mse_k16384": 0.47171084593981505,
      "continuous_q_warmup": 0.0,
      "used_k16384": 10056.0,
      "ppl_k16384": 3820.9622376527986,
      "ppl_ratio_k16384": 0.2332130272004882,
      "top1_k16384": 0.021010416666666667,
      "tokens_per_image_k16384": 240.0,
      "bits_per_image_k16384": 3360.0,
      "bpp_k16384": 0.05126953125
    }
  },
  {
    "epoch": 15,
    "train": {
      "loss": 0.015602509276941418,
      "loss_recon": 0.0021463760518236085,
      "loss_vq": 0.5697750793397427,
      "loss_monotonic": 0.0,
      "loss_q_relevance": 0.0,
      "loss_zero_anchor": 0.0,
      "loss_direct_gain": 0.0,
      "loss_teacher_final": 0.0020606318727368488,
      "loss_teacher_u2": 0.014113607418257743,
      "loss_prior_ce": 0.0,
      "loss_predictability": 0.0,
      "prior_assignment_entropy": 0.0,
      "prior_index_accuracy": 0.0,
      "loss_soft_usage": 0.0,
      "soft_usage_entropy_ratio": 0.0,
      "psnr_x1": 30.587076835632324,
      "psnr_source_teacher": 43.272816848754886,
      "delta_x1_source_teacher": 12.685740094184876,
      "train_channels_kept_mean": 176.48625,
      "psnr_k16384": 30.645035800933837,
      "delta_x1_k16384": 0.05795908927917481,
      "vq_mse_k16384": 0.4558200638741255,
      "continuous_q_warmup": 0.0,
      "used_k16384": 9947.0,
      "ppl_k16384": 3614.4464109437686,
      "ppl_ratio_k16384": 0.22060830144920462,
      "top1_k16384": 0.024140625,
      "tokens_per_image_k16384": 240.0,
      "bits_per_image_k16384": 3360.0,
      "bpp_k16384": 0.05126953125
    },
    "val": {
      "loss": 0.024633864536881447,
      "loss_recon": 0.0026555375009775163,
      "loss_vq": 0.9709935188293457,
      "loss_monotonic": 0.0,
      "loss_q_relevance": 0.0,
      "loss_zero_anchor": 0.0,
      "loss_direct_gain": 0.0,
      "loss_teacher_final": 0.002558457124978304,
      "loss_teacher_u2": 0.011999278664588928,
      "loss_prior_ce": 0.0,
      "loss_predictability": 0.0,
      "prior_assignment_entropy": 0.0,
      "prior_index_accuracy": 0.0,
      "loss_soft_usage": 0.0,
      "soft_usage_entropy_ratio": 0.0,
      "psnr_x1": 27.565001678466796,
      "psnr_source_teacher": 42.273160247802736,
      "delta_x1_source_teacher": 14.70815818786621,
      "psnr_k16384": 27.749960327148436,
      "delta_x1_k16384": 0.1849580764770508,
      "vq_mse_k16384": 0.7767948031425476,
      "drop_zero_k16384": 0.18495805740356444,
      "drop_shuffle_k16384": 0.8848606872558594,
      "continuous_q_warmup": 0.0,
      "used_k16384": 6821.0,
      "ppl_k16384": 4961.3497490080235,
      "ppl_ratio_k16384": 0.302816757141603,
      "top1_k16384": 0.0022916666666666667,
      "tokens_per_image_k16384": 240.0,
      "bits_per_image_k16384": 3360.0,
      "bpp_k16384": 0.05126953125,
      "codebook_l2_mean": 12.574150085449219,
      "codebook_l2_std": 6.037489891052246,
      "codebook_l2_min": 0.015383432619273663,
      "codebook_l2_max": 66.9473876953125,
      "codebook_l2_sample_size": 512.0,
      "codebook_effective_rank": 240.80555725097656,
      "codebook_stable_rank": 8.470596313476562,
      "codebook_numerical_rank": 256.0,
      "codebook_singular_top1_share": 0.02327696792781353,
      "codebook_rank_sample_size": 2048.0,
      "capacity_goal_met": 1.0,
      "noncollapse_goal_met": 1.0,
      "oracle_goal_met": 1.0
    }
  },
  {
    "epoch": 16,
    "train": {
      "loss": 0.015934788282029332,
      "loss_recon": 0.0022440173826180397,
      "loss_vq": 0.5766506081819535,
      "loss_monotonic": 0.0,
      "loss_q_relevance": 0.0,
      "loss_zero_anchor": 0.0,
      "loss_direct_gain": 0.0,
      "loss_teacher_final": 0.0021577591568348,
      "loss_teacher_u2": 0.01287586526479572,
      "loss_prior_ce": 0.0,
      "loss_predictability": 0.0,
      "prior_assignment_entropy": 0.0,
      "prior_index_accuracy": 0.0,
      "loss_soft_usage": 0.0,
      "soft_usage_entropy_ratio": 0.0,
      "psnr_x1": 30.53652584075928,
      "psnr_source_teacher": 43.31682975769043,
      "delta_x1_source_teacher": 12.780303974151611,
      "train_channels_kept_mean": 170.49125,
      "psnr_k16384": 30.603610382080078,
      "delta_x1_k16384": 0.06708431720733643,
      "vq_mse_k16384": 0.4613204865157604,
      "continuous_q_warmup": 0.0,
      "used_k16384": 10143.0,
      "ppl_k16384": 3552.91990625578,
      "ppl_ratio_k16384": 0.21685302162205689,
      "top1_k16384": 0.026927083333333334,
      "tokens_per_image_k16384": 240.0,
      "bits_per_image_k16384": 3360.0,
      "bpp_k16384": 0.05126953125
    }
  },
  {
    "epoch": 17,
    "train": {
      "loss": 0.016559928297065197,
      "loss_recon": 0.002264846143661998,
      "loss_vq": 0.6057943727076054,
      "loss_monotonic": 0.0,
      "loss_q_relevance": 0.0,
      "loss_zero_anchor": 0.0,
      "loss_direct_gain": 0.0,
      "loss_teacher_final": 0.0021791949635371565,
      "loss_teacher_u2": 0.013516816208139062,
      "loss_prior_ce": 0.0,
      "loss_predictability": 0.0,
      "prior_assignment_entropy": 0.0,
      "prior_index_accuracy": 0.0,
      "loss_soft_usage": 0.0,
      "soft_usage_entropy_ratio": 0.0,
      "psnr_x1": 30.25416887283325,
      "psnr_source_teacher": 43.153859252929685,
      "delta_x1_source_teacher": 12.899690389633179,
      "train_channels_kept_mean": 180.2,
      "psnr_k16384": 30.317864837646486,
      "delta_x1_k16384": 0.06369585037231446,
      "vq_mse_k16384": 0.4846354982256889,
      "continuous_q_warmup": 0.0,
      "used_k16384": 10286.0,
      "ppl_k16384": 3790.8622997299913,
      "ppl_ratio_k16384": 0.23137587278625435,
      "top1_k16384": 0.02371875,
      "tokens_per_image_k16384": 240.0,
      "bits_per_image_k16384": 3360.0,
      "bpp_k16384": 0.05126953125
    }
  },
  {
    "epoch": 18,
    "train": {
      "loss": 0.016775882723741233,
      "loss_recon": 0.0023333579301834106,
      "loss_vq": 0.6098178195953369,
      "loss_monotonic": 0.0,
      "loss_q_relevance": 0.0,
      "loss_zero_anchor": 0.0,
      "loss_direct_gain": 0.0,
      "loss_teacher_final": 0.0022461686190217733,
      "loss_teacher_u2": 0.012788637331686914,
      "loss_prior_ce": 0.0,
      "loss_predictability": 0.0,
      "prior_assignment_entropy": 0.0,
      "prior_index_accuracy": 0.0,
      "loss_soft_usage": 0.0,
      "soft_usage_entropy_ratio": 0.0,
      "psnr_x1": 30.27676082611084,
      "psnr_source_teacher": 43.24093479156494,
      "delta_x1_source_teacher": 12.964173793792725,
      "train_channels_kept_mean": 171.435,
      "psnr_k16384": 30.34156499862671,
      "delta_x1_k16384": 0.0648042356967926,
      "vq_mse_k16384": 0.487854256182909,
      "continuous_q_warmup": 0.0,
      "used_k16384": 10393.0,
      "ppl_k16384": 3711.75471831597,
      "ppl_ratio_k16384": 0.22654752919408996,
      "top1_k16384": 0.023578125,
      "tokens_per_image_k16384": 240.0,
      "bits_per_image_k16384": 3360.0,
      "bpp_k16384": 0.05126953125
    }
  },
  {
    "epoch": 19,
    "train": {
      "loss": 0.016307681193575264,
      "loss_recon": 0.0021872411502408796,
      "loss_vq": 0.6007355453073978,
      "loss_monotonic": 0.0,
      "loss_q_relevance": 0.0,
      "loss_zero_anchor": 0.0,
      "loss_direct_gain": 0.0,
      "loss_teacher_final": 0.002105729356117081,
      "loss_teacher_u2": 0.013685392853803933,
      "loss_prior_ce": 0.0,
      "loss_predictability": 0.0,
      "prior_assignment_entropy": 0.0,
      "prior_index_accuracy": 0.0,
      "loss_soft_usage": 0.0,
      "soft_usage_entropy_ratio": 0.0,
      "psnr_x1": 30.51241949081421,
      "psnr_source_teacher": 43.24130447387695,
      "delta_x1_source_teacher": 12.728884902000427,
      "train_channels_kept_mean": 177.305,
      "psnr_k16384": 30.564628047943117,
      "delta_x1_k16384": 0.05220839619636536,
      "vq_mse_k16384": 0.4805884371697903,
      "continuous_q_warmup": 0.0,
      "used_k16384": 10291.0,
      "ppl_k16384": 3522.05956546267,
      "ppl_ratio_k16384": 0.21496945589982117,
      "top1_k16384": 0.025359375,
      "tokens_per_image_k16384": 240.0,
      "bits_per_image_k16384": 3360.0,
      "bpp_k16384": 0.05126953125
    }
  },
  {
    "epoch": 20,
    "train": {
      "loss": 0.016841156724840402,
      "loss_recon": 0.0022635569621343166,
      "loss_vq": 0.6200450840219855,
      "loss_monotonic": 0.0,
      "loss_q_relevance": 0.0,
      "loss_zero_anchor": 0.0,
      "loss_direct_gain": 0.0,
      "loss_teacher_final": 0.002176698465482332,
      "loss_teacher_u2": 0.01420819118618965,
      "loss_prior_ce": 0.0,
      "loss_predictability": 0.0,
      "prior_assignment_entropy": 0.0,
      "prior_index_accuracy": 0.0,
      "loss_soft_usage": 0.0,
      "soft_usage_entropy_ratio": 0.0,
      "psnr_x1": 30.621358394622803,
      "psnr_source_teacher": 43.265097846984865,
      "delta_x1_source_teacher": 12.643739805221557,
      "train_channels_kept_mean": 182.15,
      "psnr_k16384": 30.698436164855956,
      "delta_x1_k16384": 0.07707776308059693,
      "vq_mse_k16384": 0.49603606667369604,
      "continuous_q_warmup": 0.0,
      "used_k16384": 10537.0,
      "ppl_k16384": 3446.815828014062,
      "ppl_ratio_k16384": 0.2103769426278114,
      "top1_k16384": 0.03185416666666667,
      "tokens_per_image_k16384": 240.0,
      "bits_per_image_k16384": 3360.0,
      "bpp_k16384": 0.05126953125
    },
    "val": {
      "loss": 0.025248059779405595,
      "loss_recon": 0.00264507575891912,
      "loss_vq": 1.0027194833755493,
      "loss_monotonic": 0.0,
      "loss_q_relevance": 0.0,
      "loss_zero_anchor": 0.0,
      "loss_direct_gain": 0.0,
      "loss_teacher_final": 0.002548595191910863,
      "loss_teacher_u2": 0.011983706764876843,
      "loss_prior_ce": 0.0,
      "loss_predictability": 0.0,
      "prior_assignment_entropy": 0.0,
      "prior_index_accuracy": 0.0,
      "loss_soft_usage": 0.0,
      "soft_usage_entropy_ratio": 0.0,
      "psnr_x1": 27.565001678466796,
      "psnr_source_teacher": 42.273160247802736,
      "delta_x1_source_teacher": 14.70815818786621,
      "psnr_k16384": 27.764729461669923,
      "delta_x1_k16384": 0.19972702026367187,
      "vq_mse_k16384": 0.8021755981445312,
      "drop_zero_k16384": 0.19972700119018555,
      "drop_shuffle_k16384": 0.8995572090148926,
      "continuous_q_warmup": 0.0,
      "used_k16384": 6898.0,
      "ppl_k16384": 4884.008713862727,
      "ppl_ratio_k16384": 0.2980962349769731,
      "top1_k16384": 0.00425,
      "tokens_per_image_k16384": 240.0,
      "bits_per_image_k16384": 3360.0,
      "bpp_k16384": 0.05126953125,
      "codebook_l2_mean": 12.573721885681152,
      "codebook_l2_std": 6.037680625915527,
      "codebook_l2_min": 0.01948779821395874,
      "codebook_l2_max": 66.9473876953125,
      "codebook_l2_sample_size": 512.0,
      "codebook_effective_rank": 240.80462646484375,
      "codebook_stable_rank": 8.470348358154297,
      "codebook_numerical_rank": 256.0,
      "codebook_singular_top1_share": 0.023277414962649345,
      "codebook_rank_sample_size": 2048.0,
      "capacity_goal_met": 1.0,
      "noncollapse_goal_met": 1.0,
      "oracle_goal_met": 1.0
    }
  },
  {
    "epoch": 21,
    "train": {
      "loss": 0.017839186997152864,
      "loss_recon": 0.0023818415595451368,
      "loss_vq": 0.6585722589492797,
      "loss_monotonic": 0.0,
      "loss_q_relevance": 0.0,
      "loss_zero_anchor": 0.0,
      "loss_direct_gain": 0.0,
      "loss_teacher_final": 0.0022859005286591126,
      "loss_teacher_u2": 0.013476136475801467,
      "loss_prior_ce": 0.0,
      "loss_predictability": 0.0,
      "prior_assignment_entropy": 0.0,
      "prior_index_accuracy": 0.0,
      "loss_soft_usage": 0.0,
      "soft_usage_entropy_ratio": 0.0,
      "psnr_x1": 30.221203174591064,
      "psnr_source_teacher": 43.17189167022705,
      "delta_x1_source_teacher": 12.950688438415527,
      "train_channels_kept_mean": 179.21625,
      "psnr_k16384": 30.31169485092163,
      "delta_x1_k16384": 0.09049184560775757,
      "vq_mse_k16384": 0.5268578061461449,
      "continuous_q_warmup": 0.0,
      "used_k16384": 10671.0,
      "ppl_k16384": 3782.476861981342,
      "ppl_ratio_k16384": 0.2308640662830409,
      "top1_k16384": 0.02659375,
      "tokens_per_image_k16384": 240.0,
      "bits_per_image_k16384": 3360.0,
      "bpp_k16384": 0.05126953125
    }
  },
  {
    "epoch": 22,
    "train": {
      "loss": 0.01743543891236186,
      "loss_recon": 0.002316227321862243,
      "loss_vq": 0.6446023474633694,
      "loss_monotonic": 0.0,
      "loss_q_relevance": 0.0,
      "loss_zero_anchor": 0.0,
      "loss_direct_gain": 0.0,
      "loss_teacher_final": 0.0022271649772301317,
      "loss_teacher_u2": 0.012954261298291385,
      "loss_prior_ce": 0.0,
      "loss_predictability": 0.0,
      "prior_assignment_entropy": 0.0,
      "prior_index_accuracy": 0.0,
      "loss_soft_usage": 0.0,
      "soft_usage_entropy_ratio": 0.0,
      "psnr_x1": 30.335532245635985,
      "psnr_source_teacher": 43.215235481262205,
      "delta_x1_source_teacher": 12.879702796936035,
      "train_channels_kept_mean": 175.7725,
      "psnr_k16384": 30.41825216293335,
      "delta_x1_k16384": 0.08271939754486084,
      "vq_mse_k16384": 0.5156818752735853,
      "continuous_q_warmup": 0.0,
      "used_k16384": 10678.0,
      "ppl_k16384": 3645.563789387161,
      "ppl_ratio_k16384": 0.22250755550458745,
      "top1_k16384": 0.02896875,
      "tokens_per_image_k16384": 240.0,
      "bits_per_image_k16384": 3360.0,
      "bpp_k16384": 0.05126953125
    }
  },
  {
    "epoch": 23,
    "train": {
      "loss": 0.017959440117701887,
      "loss_recon": 0.002249724263092503,
      "loss_vq": 0.6773625843226909,
      "loss_monotonic": 0.0,
      "loss_q_relevance": 0.0,
      "loss_zero_anchor": 0.0,
      "loss_direct_gain": 0.0,
      "loss_teacher_final": 0.002162464635330252,
      "loss_teacher_u2": 0.013612922427710146,
      "loss_prior_ce": 0.0,
      "loss_predictability": 0.0,
      "prior_assignment_entropy": 0.0,
      "prior_index_accuracy": 0.0,
      "loss_soft_usage": 0.0,
      "soft_usage_entropy_ratio": 0.0,
      "psnr_x1": 30.370207748413087,
      "psnr_source_teacher": 43.24340167999267,
      "delta_x1_source_teacher": 12.873193464279176,
      "train_channels_kept_mean": 188.24375,
      "psnr_k16384": 30.459208145141602,
      "delta_x1_k16384": 0.08900032758712768,
      "vq_mse_k16384": 0.5418900660425424,
      "continuous_q_warmup": 0.0,
      "used_k16384": 10640.0,
      "ppl_k16384": 3688.251743347118,
      "ppl_ratio_k16384": 0.22511302144452625,
      "top1_k16384": 0.027213541666666667,
      "tokens_per_image_k16384": 240.0,
      "bits_per_image_k16384": 3360.0,
      "bpp_k16384": 0.05126953125
    }
  }
]